qosst_skr/__init__.py
qosst_skr/gaussian_trusted_heterodyne_asymptotic.py
qosst_skr/gaussian_trusted_homodyne_asymptotic.py
qosst_skr/gaussian_untrusted_homodyne_asymptotic.py
qosst_skr/py.typed
qosst_skr/utils.py
qosst_skr-0.10.0.dist-info/LICENSE
qosst_skr-0.10.0.dist-info/METADATA
qosst_skr-0.10.0.dist-info/WHEEL
qosst_skr-0.10.0.dist-info/RECORD
